bit_diffusion/__init__.py
bit_diffusion/bit_diffusion.py
bit_diffusion-0.1.4.dist-info/LICENSE
bit_diffusion-0.1.4.dist-info/METADATA
bit_diffusion-0.1.4.dist-info/WHEEL
bit_diffusion-0.1.4.dist-info/top_level.txt
bit_diffusion-0.1.4.dist-info/RECORD
