Metadata-Version: 2.1
Name: bit-diffusion
Version: 0.1.4
Summary: Bit Diffusion - Pytorch
Home-page: https://github.com/lucidrains/bit-diffusion
Author: Phil Wang
Author-email: lucidrains@gmail.com
License: MIT
Keywords: artificial intelligence,deep learning,denoising diffusion
Classifier: Development Status :: 4 - Beta
Classifier: Intended Audience :: Developers
Classifier: Topic :: Scientific/Engineering :: Artificial Intelligence
Classifier: License :: OSI Approved :: MIT License
Classifier: Programming Language :: Python :: 3.6
License-File: LICENSE
Requires-Dist: accelerate
Requires-Dist: einops
Requires-Dist: ema-pytorch
Requires-Dist: pillow
Requires-Dist: torch >=1.12.0
Requires-Dist: torchvision
Requires-Dist: tqdm
